[
    {
        "id": 1,
        "Departure": "Ezeiza",
        "Reach": "Bogota",
        "departureDate": "",
        "ReturnDate": "",
        "departureHour": "",
        "returnHour": "",
        "hotel": "Hilton",
        "description": " Lorem ipsum dolor sit amet consectetur adipisicing elit. Fuga quos, quisquam possimus neque nisi eos nam mollitia voluptatibus repudiandae simi, dicta architecto fugit corrupti eius aliquam ex dolor placeat assumenda.",
        "cabin": "Premium",
        "service": 4,
        "passengers": 3,
        "onSale": true,
        "price": 3500
    },
    {
        "id": 2,
        "Departure": "Ezeiza",
        "Reach": "Miami",
        "departureDate": "",
        "ReturnDate": "",
        "departureHour": "",
        "returnHour": "",
        "hotel":"Hilton",
        "description": " Lorem ipsum dolor sit amet consectetur adipisicing elit. Fuga quos, quisquam possimus neque nisi eos nam mollitia voluptatibus repudiandae simi, dicta architecto fugit corrupti eius aliquam ex dolor placeat assumenda.",
        "cabin": "Economy",
        "service": 4,
        "passengers": 4,
        "onSale": false,
        "price": 3500
    },
    {
        "id": 3,
        "Departure": "Ezeiza",
        "Reach": "Maracaibo",
        "departureDate": "",
        "ReturnDate": "",
        "departureHour": "",
        "returnHour": "",
        "hotel":"Hilton",
        "description": " Lorem ipsum dolor sit amet consectetur adipisicing elit. Fuga quos, quisquam possimus neque nisi eos nam mollitia voluptatibus repudiandae simi, dicta architecto fugit corrupti eius aliquam ex dolor placeat assumenda.",
        "cabin": "Premium vip",
        "service": 3,
        "passengers": 1,
        "onSale": true,
        "price": 3500
    },
    {
        "id": 4,
        "Departure": "Ezeiza",
        "Reach": "China",
        "departureDate": "",
        "ReturnDate": "",
        "departureHour": "",
        "returnHour": "",
        "hotel":"Hilton",
        "description": " Lorem ipsum dolor sit amet consectetur adipisicing elit. Fuga quos, quisquam possimus neque nisi eos nam mollitia voluptatibus repudiandae simi, dicta architecto fugit corrupti eius aliquam ex dolor placeat assumenda.",
        "cabin": "Premium",
        "service": 3,
        "passengers": 2,
        "onSale": false,
        "price": 3500
    },
    {
        "id": 5,
        "Departure": "Ezeiza",
        "Reach": "Rusia",
        "departureDate": "",
        "ReturnDate": "",
        "departureHour": "",
        "returnHour": "",
        "hotel":"Hilton",
        "description": " Lorem ipsum dolor sit amet consectetur adipisicing elit. Fuga quos, quisquam possimus neque nisi eos nam mollitia voluptatibus repudiandae simi, dicta architecto fugit corrupti eius aliquam ex dolor placeat assumenda.",
        "cabin": "Economy",
        "service": 4,
        "passengers": 3,
        "onSale": true,
        "price": 3500
    },
    {
        "id": 6,
        "Departure": "Ezeiza",
        "Reach": "Australia",
        "departureDate": "",
        "ReturnDate": "",
        "departureHour": "",
        "returnHour": "",
        "hotel":"Hilton",
        "description": " Lorem ipsum dolor sit amet consectetur adipisicing elit. Fuga quos, quisquam possimus neque nisi eos nam mollitia voluptatibus repudiandae simi, dicta architecto fugit corrupti eius aliquam ex dolor placeat assumenda.",
        "cabin": "Premium vip",
        "service": 5,
        "passengers": 3,
        "onSale": false,
        "price": 3500
    }
]